atooms/__init__.py
atooms/database/__init__.py
atooms/database/_cutoffs.py
atooms/database/_models.json
atooms/database/_potentials.py
atooms/database/_samples.json
atooms/database/_schemas.py
atooms/database/database.py
atooms/database/helpers.py
atooms/database/hooks.py
atooms/database/schema.py
atooms/database/f90/__init__.py
atooms/database/rumd/__init__.py
atooms/database/rumd/interaction.py
atooms/database/storage/bernu_hiwatari_hansen_pastore/0_f61d7e58b9656cf9640f6e5754441930.xyz
atooms/database/storage/coslovich_pastore/0_488db481cdac35e599922a26129c3e35.xyz
atooms/database/storage/grigera_cavagna_giardina_parisi/0_0ac97fa8c69c320e48bd1fca80855e8a.xyz
atooms/database/storage/kob_andersen/0_8f4a9fe755e5c1966c10b50c9a53e6bf.xyz
atooms/database/storage/lennard_jones/0_13ce47602b259f7802e89e23ffd57f19.xyz
atooms/database/storage/lennard_jones/0_5cc3b80bc415fa5c262e83410ca65779.xyz
atooms_database-0.3.1.dist-info/LICENSE
atooms_database-0.3.1.dist-info/METADATA
atooms_database-0.3.1.dist-info/WHEEL
atooms_database-0.3.1.dist-info/top_level.txt
atooms_database-0.3.1.dist-info/RECORD
