Metadata-Version: 2.1
Name: atooms-database
Version: 0.3.1
Summary: Database of interaction database for classical molecular dynamics and Monte Carlo simulations
Home-page: https://framagit.org/atooms/database
Author: Daniele Coslovich
Author-email: dcoslovich@units.it
License: GPLv3
Platform: UNKNOWN
Classifier: License :: OSI Approved :: GNU General Public License v3 (GPLv3)
Classifier: Programming Language :: Python
Classifier: Programming Language :: Python :: 2
Classifier: Programming Language :: Python :: 2.7
Classifier: Programming Language :: Python :: 3
Classifier: Programming Language :: Python :: 3.6
License-File: LICENSE
Requires-Dist: atooms (~=3.19)
Requires-Dist: f2py-jit (~=0.5)
Requires-Dist: jsonschema
Requires-Dist: tinydb
Requires-Dist: tqdm
